calico/__init__.py
calico/_calico.cpython-310-x86_64-linux-gnu.so
calico/utils.py
calico_python.libs/libgfortran-91cc3cb1.so.3.0.0
calico_python.libs/libopencv_flann-f97a0cbc.so.2.4.5
calico_python.libs/libharfbuzz-77c15733.so.0.10705.0
calico_python.libs/libgtk-x11-2-4729d4a9.0.so.0.2400.31
calico_python.libs/libopencv_contrib-25ad0d13.so.2.4.5
calico_python.libs/libpcre-9513aab5.so.1.2.0
calico_python.libs/liborc-0-14d3dc57.4.so.0.25.0
calico_python.libs/libgstreamer-0-b9f61d5a.10.so.0.30.0
calico_python.libs/libpangocairo-1-b80816ef.0.so.0.4200.3
calico_python.libs/libopencv_features2d-efdcd09e.so.2.4.5
calico_python.libs/libopencv_superres-2ffef534.so.2.4.5
calico_python.libs/libopencv_stitching-e76279fb.so.2.4.5
calico_python.libs/libblas-357956a1.so.3.4.2
calico_python.libs/libgstapp-0-a5c3a46f.10.so.0.25.0
calico_python.libs/libmount-2c8ae47c.so.1.1.0
calico_python.libs/libv4l2-3017b2f2.so.0.0.0
calico_python.libs/libopencv_highgui-8bf9344d.so.2.4.5
calico_python.libs/liblzma-004595ca.so.5.2.2
calico_python.libs/libjbig-78348776.so.2.0
calico_python.libs/libquadmath-96973f99.so.0.0.0
calico_python.libs/libIexMath-ffbe7dee.so.6.0.0
calico_python.libs/libselinux-0922c95c.so.1
calico_python.libs/libthai-b24067ec.so.0.1.6
calico_python.libs/libHalf-fab309d1.so.6.0.0
calico_python.libs/libGLdispatch-dcc1ca97.so.0.0.0
calico_python.libs/libEGL-29b68110.so.1.1.0
calico_python.libs/libatk-1-6b75be46.0.so.0.22810.1
calico_python.libs/libXrandr-1b5fae8f.so.2.2.0
calico_python.libs/libglog-2ac4fad0.so.0.0.0
calico_python.libs/libgdk_pixbuf-2-fd592e6b.0.so.0.3612.0
calico_python.libs/libIlmThread-04f44d01.so.6.0.0
calico_python.libs/libopencv_videostab-4e07043f.so.2.4.5
calico_python.libs/libXi-e28fba09.so.6.1.0
calico_python.libs/libffi-af4ed708.so.6.0.1
calico_python.libs/libgstbase-0-c8e8ab2f.10.so.0.30.0
calico_python.libs/libXdamage-b7595c70.so.1.1.0
calico_python.libs/libIlmImf-779f48be.so.7.0.0
calico_python-0.0.1.dist-info/RECORD
calico_python-0.0.1.dist-info/METADATA
calico_python-0.0.1.dist-info/LICENSE
calico_python-0.0.1.dist-info/WHEEL
calico_python-0.0.1.dist-info/top_level.txt
