Metadata-Version: 2.1
Name: calico-python
Version: 0.0.1
Summary: A visual-inertial calibration library designed for rapid problem construction and debugging.
Author-email: James Yang <james.yang92@gmail.com>
License: MIT License
Project-URL: Homepage, https://github.com/yangjames/Calico.git
Classifier: Development Status :: 5 - Production/Stable
Classifier: Intended Audience :: Developers
Classifier: Intended Audience :: Science/Research
Classifier: License :: OSI Approved :: MIT License
Classifier: Operating System :: Unix
Classifier: Programming Language :: Python
License-File: LICENSE
